ledgercomm/__init__.py
ledgercomm/__version__.py
ledgercomm/log.py
ledgercomm/transport.py
ledgercomm/cli/__init__.py
ledgercomm/cli/send.py
ledgercomm/interfaces/__init__.py
ledgercomm/interfaces/comm.py
ledgercomm/interfaces/hid_device.py
ledgercomm/interfaces/tcp_client.py
ledgercomm-1.2.1.dist-info/LICENCE
ledgercomm-1.2.1.dist-info/METADATA
ledgercomm-1.2.1.dist-info/WHEEL
ledgercomm-1.2.1.dist-info/entry_points.txt
ledgercomm-1.2.1.dist-info/top_level.txt
ledgercomm-1.2.1.dist-info/zip-safe
ledgercomm-1.2.1.dist-info/RECORD
