Metadata-Version: 2.1
Name: ledgercomm
Version: 1.2.1
Summary: Library to communicate with Ledger Nano S/X and Speculos
Home-page: https://github.com/LedgerHQ/ledgercomm
Author: Ledger
Author-email: hello@ledger.fr
Project-URL: Bug Tracker, https://github.com/LedgerHQ/ledgercomm/issues
Classifier: Development Status :: 5 - Production/Stable
Classifier: Environment :: Console
Classifier: License :: OSI Approved :: MIT License
Classifier: Programming Language :: Python :: 3.8
Classifier: Programming Language :: Python :: 3.9
Classifier: Operating System :: POSIX
Requires-Python: >=3.8
License-File: LICENCE
Provides-Extra: hid
Requires-Dist: hidapi>=0.9.0.post3; extra == "hid"
